python_loki_logger/Logger.py
python_loki_logger/__init__.py
python_loki_logger/exceptions.py
python_loki_logger-3.0.0.dist-info/licenses/LICENSE
python_loki_logger-3.0.0.dist-info/METADATA
python_loki_logger-3.0.0.dist-info/WHEEL
python_loki_logger-3.0.0.dist-info/top_level.txt
python_loki_logger-3.0.0.dist-info/RECORD
