Metadata-Version: 2.4
Name: python-loki-logger
Version: 3.0.0
Summary: A Python Library for pushing logs to Grafana-Loki
Author: Piyush Manolkar
Author-email: Piyush Manolkar <manolkarpiyush@gmail.com>
License: MIT
Project-URL: Homepage, https://github.com/piyushmanolkar/python-loki-logger
Project-URL: Repository, https://github.com/piyushmanolkar/python-loki-logger
Project-URL: Issues, https://github.com/piyushmanolkar/python-loki-logger/issues
Keywords: loki,grafana,logging,observability,logs
Classifier: Intended Audience :: Developers
Classifier: License :: OSI Approved :: MIT License
Classifier: Programming Language :: Python
Classifier: Programming Language :: Python :: 3
Classifier: Programming Language :: Python :: 3.8
Classifier: Programming Language :: Python :: 3.9
Classifier: Programming Language :: Python :: 3.10
Classifier: Programming Language :: Python :: 3.11
Classifier: Programming Language :: Python :: 3.12
Classifier: Operating System :: OS Independent
Requires-Python: >=3.8
License-File: LICENSE
Requires-Dist: requests>=2.25.0
Provides-Extra: dev
Requires-Dist: pytest>=7.0.0; extra == "dev"
Requires-Dist: pytest-cov>=4.0.0; extra == "dev"
Requires-Dist: pytest-mock>=3.10.0; extra == "dev"
Requires-Dist: requests-mock>=1.9.3; extra == "dev"
Requires-Dist: black>=22.0.0; extra == "dev"
Requires-Dist: flake8>=5.0.0; extra == "dev"
Requires-Dist: mypy>=1.0.0; extra == "dev"
Requires-Dist: types-requests>=2.28.0; extra == "dev"
Dynamic: author
Dynamic: license-file
Dynamic: requires-python
